web_scraping_framework/__init__.py
web_scraping_framework/base/__init__.py
web_scraping_framework/base/multiprocessing_log_handler.py
web_scraping_framework/base/multiprocessing_logger.py
web_scraping_framework/bin/CustomApp.py
web_scraping_framework/bin/CustomModels.py
web_scraping_framework/bin/__init__.py
web_scraping_framework/bin/tasks.py
web_scraping_framework/modules/__init__.py
web_scraping_framework/modules/pagination_page_change_detection_webservice/__init__.py
web_scraping_framework/modules/pagination_page_change_detection_webservice/pagination_page_change_detection.py
web_scraping_framework/modules/pagination_page_change_detection_webservice/pagination_page_change_detection_webservice.py
web_scraping_framework/modules/template_matching_webservice/__init__.py
web_scraping_framework/modules/template_matching_webservice/template_matching.py
web_scraping_framework/modules/template_matching_webservice/template_matching_webservice.py
web_scraping_framework/tests/__init__.py
web_scraping_framework/tests/unittest_base_multiprocessing_logger.py
web_scraping_framework/tests/unittest_base_settings.py
web_scraping_framework-0.6.dist-info/METADATA
web_scraping_framework-0.6.dist-info/WHEEL
web_scraping_framework-0.6.dist-info/top_level.txt
web_scraping_framework-0.6.dist-info/RECORD
